tools/__init__.py
tools/asciinema.py
tools/case_study_generator.py
tools/claude.bash
tools/gif.py
tools/logs.py
tools/replay.py
tools/templates/case-study.php
cai/__init__.py
cai/cli.py
cai/util.py
cai/agents/__init__.py
cai/agents/android_sast_agent.py
cai/agents/blue_teamer.py
cai/agents/bug_bounter.py
cai/agents/codeagent.py
cai/agents/dfir.py
cai/agents/factory.py
cai/agents/flag_discriminator.py
cai/agents/guardrails.py
cai/agents/mail.py
cai/agents/memory.py
cai/agents/memory_analysis_agent.py
cai/agents/network_traffic_analyzer.py
cai/agents/one_tool.py
cai/agents/red_teamer.py
cai/agents/replay_attack_agent.py
cai/agents/reporter.py
cai/agents/retester.py
cai/agents/reverse_engineering_agent.py
cai/agents/subghz_sdr_agent.py
cai/agents/thought.py
cai/agents/usecase.py
cai/agents/wifi_security_tester.py
cai/agents/meta/local_python_executor.py
cai/agents/meta/reasoner_support.py
cai/agents/patterns/__init__.py
cai/agents/patterns/bb_triage.py
cai/agents/patterns/offsec.py
cai/agents/patterns/parallel_offensive_patterns.py
cai/agents/patterns/pattern.py
cai/agents/patterns/red_blue_team.py
cai/agents/patterns/red_blue_team_split.py
cai/agents/patterns/red_team.py
cai/agents/patterns/utils.py
cai/agents/patterns/configs/agents.yml.example
cai/internal/__init__.py
cai/internal/components/__init__.py
cai/internal/components/endpoints.py
cai/internal/components/metrics.py
cai/internal/components/network.py
cai/internal/components/transfer.py
cai/prompts/memory_analysis_agent.md
cai/prompts/reverse_engineering_agent.md
cai/prompts/subghz_agent.md
cai/prompts/system_android_app_logic_mapper.md
cai/prompts/system_android_sast.md
cai/prompts/system_blue_team_agent.md
cai/prompts/system_bug_bounter.md
cai/prompts/system_dfir_agent.md
cai/prompts/system_exploit_expert.md
cai/prompts/system_network_analyzer.md
cai/prompts/system_reasoner_supporter.md
cai/prompts/system_red_team_agent.md
cai/prompts/system_replay_attack_agent.md
cai/prompts/system_reporting_agent.md
cai_framework-0.5.5.dist-info/METADATA
cai_framework-0.5.5.dist-info/WHEEL
cai_framework-0.5.5.dist-info/entry_points.txt
cai_framework-0.5.5.dist-info/licenses/LICENSE
cai_framework-0.5.5.dist-info/licenses/LICENSE-MIT
cai_framework-0.5.5.dist-info/RECORD
