Metadata-Version: 2.4
Name: cai-framework
Version: 0.5.5
Summary: Cybersecurity AI Framework
Project-URL: Homepage, https://github.com/openai/openai-agents-python
Project-URL: Repository, https://github.com/openai/openai-agents-python
Author-email: Alias Robotics <research@aliasrobotics.com>
License: Dual-licensed MIT and Proprietary
License-File: LICENSE
License-File: LICENSE-MIT
Classifier: Intended Audience :: Developers
Classifier: License :: OSI Approved :: MIT License
Classifier: Operating System :: OS Independent
Classifier: Programming Language :: Python :: 3
Classifier: Programming Language :: Python :: 3.9
Classifier: Programming Language :: Python :: 3.10
Classifier: Programming Language :: Python :: 3.11
Classifier: Programming Language :: Python :: 3.12
Classifier: Topic :: Software Development :: Libraries :: Python Modules
Classifier: Typing :: Typed
Requires-Python: >=3.9
Requires-Dist: dnspython
Requires-Dist: dotenv>=0.9.9
Requires-Dist: flask
Requires-Dist: folium<1,>=0.15.0
Requires-Dist: griffe<2,>=1.5.6
Requires-Dist: litellm[proxy]>=1.63.7
Requires-Dist: mako>=1.3.8
Requires-Dist: matplotlib<4,>=3.0
Requires-Dist: mcp; python_version >= '3.10'
Requires-Dist: mkdocs-material>=9.6.0
Requires-Dist: mkdocs>=1.6.0
Requires-Dist: networkx
Requires-Dist: numpy<3,>=1.21
Requires-Dist: openai==1.75.0
Requires-Dist: openinference-instrumentation-openai>=0.1.22
Requires-Dist: pandas<3,>=1.3
Requires-Dist: paramiko>=3.5.1
Requires-Dist: prompt-toolkit>=3.0.39
Requires-Dist: pydantic<3,>=2.10
Requires-Dist: pypdf2
Requires-Dist: requests<3,>=2.0
Requires-Dist: rich>=13.9.4
Requires-Dist: types-requests<3,>=2.0
Requires-Dist: typing-extensions<5,>=4.12.2
Requires-Dist: wasabi>=1.1.3
Provides-Extra: viz
Requires-Dist: graphviz>=0.17; extra == 'viz'
Provides-Extra: voice
Requires-Dist: numpy<3,>=2.2.0; (python_version >= '3.10') and extra == 'voice'
Requires-Dist: websockets<16,>=15.0; extra == 'voice'
